README.md
setup.py
app/__init__.py
app/__main__.py
app/app.py
app123.egg-info/PKG-INFO
app123.egg-info/SOURCES.txt
app123.egg-info/dependency_links.txt
app123.egg-info/entry_points.txt
app123.egg-info/top_level.txt